dashai_test_image_classification_package/__init__.py
dashai_test_image_classification_package/image_classification_model.py
dashai_test_image_classification_package/image_classification_task.py
dashai_test_image_classification_package/mlp_image_classifier.py
dashai_test_image_classification_package-0.0.3.dist-info/METADATA
dashai_test_image_classification_package-0.0.3.dist-info/WHEEL
dashai_test_image_classification_package-0.0.3.dist-info/entry_points.txt
dashai_test_image_classification_package-0.0.3.dist-info/RECORD
