Metadata-Version: 2.3
Name: dashai_test_image_classification_package
Version: 0.0.3
Summary: Image Classification Package for DashAI
Project-URL: Homepage, https://github.com/DashAISoftware/DashAI
Project-URL: Issues, https://github.com/DashAISoftware/DashAI/issues
Author: DashAI team
Author-email: dashaisoftware@gmail.com
Keywords: DashAI,Model,Task
Requires-Python: >=3.8
Requires-Dist: torchvision==0.14.0
